stories/__init__.py
stories/loss.py
stories/potentials.py
stories/spacetime.py
stories/steps/__init__.py
stories/steps/explicit.py
stories/steps/icnn_implicit.py
stories/steps/monge_implicit.py
stories/steps/proximal_step.py
stories/tools.py
stories_jax-0.1.1.dist-info/METADATA
stories_jax-0.1.1.dist-info/WHEEL
stories_jax-0.1.1.dist-info/licenses/LICENSE
stories_jax-0.1.1.dist-info/RECORD
