Metadata-Version: 2.4
Name: stories-jax
Version: 0.1.1
Summary: Learn spatially informed Waddington-like potentials for single-cell gene expression
License-File: LICENSE
Author: Geert-Jan Huizing
Author-email: gjhuizing@gmail.com
Requires-Python: >=3.10,<4.0
Classifier: Programming Language :: Python :: 3
Classifier: Programming Language :: Python :: 3.10
Classifier: Programming Language :: Python :: 3.11
Classifier: Programming Language :: Python :: 3.12
Classifier: Programming Language :: Python :: 3.13
Classifier: Programming Language :: Python :: 3.14
Provides-Extra: docs
Requires-Dist: anndata (>=0.10.7,<0.11.0)
Requires-Dist: cellrank (>=2.0.4,<3.0.0)
Requires-Dist: flax (==0.8.2)
Requires-Dist: jax (==0.4.26)
Requires-Dist: jaxlib (==0.4.26)
Requires-Dist: jaxopt (>=0.8.3,<0.9.0)
Requires-Dist: myst-parser (>=3.0.1,<4.0.0) ; extra == "docs"
Requires-Dist: nbsphinx (>=0.9.4,<0.10.0) ; extra == "docs"
Requires-Dist: numpy (>=1.26.4,<2.0.0)
Requires-Dist: optax (>=0.2.2,<0.3.0)
Requires-Dist: orbax-checkpoint (>=0.5.20,<0.6.0)
Requires-Dist: ott-jax (==0.4.6)
Requires-Dist: scikit-learn (>=1.5.1,<2.0.0)
Requires-Dist: seaborn (>=0.13.2,<0.14.0)
Requires-Dist: sphinx-design (>=0.6.0,<0.7.0) ; extra == "docs"
Requires-Dist: sphinxawesome-theme (>=5.2.0,<6.0.0) ; extra == "docs"
Requires-Dist: tqdm (>=4.66.2,<5.0.0)
